README.txt
htmlist
htmlist.bat
license.txt
setup.py
HtmlList.egg-info/PKG-INFO
HtmlList.egg-info/SOURCES.txt
HtmlList.egg-info/dependency_links.txt
HtmlList.egg-info/top_level.txt
HtmlList.egg-info/zip-safe
htmllist/__init__.py
htmllist/algo_dict.py
htmllist/break_html_page.py
htmllist/break_html_page2.py
htmllist/break_page_base.py
htmllist/break_page_seq.py
htmllist/htmllist_base.py
htmllist/htmllist_break.py
htmllist/htmllist_demo.py
htmllist/htmllist_summary.py
htmllist/pattern_quality.py
htmllist/pysuffix_tools.py
htmllist/repeat_pattern.py
htmllist/repeat_pattern2.py
htmllist/repeat_pattern3.py
htmllist/repeat_pattern_base.py
htmllist/repeat_pattern_suffix.py
htmllist/repeat_title.py
htmllist/tag_tools.py
htmllist/the_problem.txt
htmllist/utills.py
htmllist/test/__init__.py
htmllist/test/amazon.html
htmllist/test/amazon.rslt
htmllist/test/amazon1.html
htmllist/test/amazon1.rslt
htmllist/test/bbc.html
htmllist/test/bbc.rslt
htmllist/test/bing.html
htmllist/test/bing.rslt
htmllist/test/cnn.html
htmllist/test/cnn.rslt
htmllist/test/cnn_world.html
htmllist/test/cnn_world.rslt
htmllist/test/ebay.html
htmllist/test/ebay.rslt
htmllist/test/google.html
htmllist/test/google.rslt
htmllist/test/noaa.html
htmllist/test/noaa.rslt
htmllist/test/npr.html
htmllist/test/npr.rslt
htmllist/test/npr_news.html
htmllist/test/npr_news.rslt
htmllist/test/oreilly.html
htmllist/test/oreilly.rslt
htmllist/test/pbs.html
htmllist/test/pbs.rslt
htmllist/test/profile.py
htmllist/test/python.html
htmllist/test/python.rslt
htmllist/test/regression_tests.py
htmllist/test/ubuntu.html
htmllist/test/ubuntu.rslt
htmllist/test/wachovia.html
htmllist/test/wachovia.rslt
htmllist/test/yahoo.html
htmllist/test/yahoo.rslt