Metadata-Version: 1.0
Name: HtmlList
Version: 2.2.1
Summary: Extract information from HTML pages that have some kind of a repetitive pattern
Home-page: http://pyhtmllist.sourceforge.net/
Author: Erez Bibi
Author-email: erezbibi@users.sourceforge.net
License: GPL
Keywords: HTML list information extraction repetitive pattern
Platform: UNKNOWN
Classifier: Development Status :: 4 - Beta
Classifier: Intended Audience :: Developers
Classifier: License :: OSI Approved :: GNU General Public License (GPL)
Classifier: Operating System :: OS Independent
Classifier: Programming Language :: Python
Classifier: Topic :: Text Processing :: Markup :: HTML
Classifier: Topic :: Utilities
